{
  "package_id": "0x34ea4b798c3164cec0984f1fb64ef45355f0f0ee913595e6658ba24913fe135d",
  "module_call_graphs": [
    {
      "module_name": "vulnerable",
      "call_graph": {
        "add_unchecked": [],
        "batch_increment": [],
        "create_counter": [
          "0x0000000000000000000000000000000000000000000000000000000000000002::object::new"
        ],
        "decrement_counter_unchecked": [],
        "divide_unchecked": [],
        "get_counter_value": [],
        "increment_counter_unchecked": [],
        "multiply_unchecked": [],
        "transfer_counter": [
          "0x0000000000000000000000000000000000000000000000000000000000000002::transfer::transfer"
        ],
        "truncate_value": [],
        "unsafe_access": []
      }
    }
  ]
}