{
  "package_id": "0x9f940d202e7e147ea512d0ea84f5d84cb9575850a95cea485d2fa94eb229d6c0",
  "module_call_graphs": [
    {
      "module_name": "math",
      "call_graph": {
        "add": [],
        "bps_round_up": [],
        "div": [],
        "div_round_up": [],
        "eq": [],
        "from": [],
        "from_apr": [],
        "from_bps": [],
        "from_percentage": [],
        "from_u128": [],
        "from_u8": [],
        "ge": [],
        "gt": [],
        "le": [],
        "lt": [],
        "max": [],
        "min": [],
        "mul": [],
        "per_day_from_apr": [],
        "per_second_from_apr": [],
        "percentage_round_up": [],
        "pow": [
          "0x9f940d202e7e147ea512d0ea84f5d84cb9575850a95cea485d2fa94eb229d6c0::math::from",
          "0x9f940d202e7e147ea512d0ea84f5d84cb9575850a95cea485d2fa94eb229d6c0::math::mul"
        ],
        "round_up_u64": [],
        "safe_sub": [],
        "sub": [],
        "to_percentage": [],
        "to_u128": [],
        "to_u64": []
      }
    }
  ]
}